{
  "rows": 815235,
  "columns": [
    "timestamp",
    "price",
    "quantity",
    "side",
    "trade_id",
    "is_gap_start",
    "segment_id",
    "price_increment",
    "log_return",
    "tick_direction",
    "trade_intensity",
    "obi",
    "obi_valid",
    "mid_price",
    "vwmp",
    "price_mid_deviation"
  ],
  "autocorrelation": {
    "1": 0.9024983199480066,
    "2": 0.8514481469467532,
    "3": 0.8156114398997191,
    "4": 0.7850922149525248,
    "5": 0.758124579803573,
    "6": 0.7333791514906819,
    "7": 0.7104888657928378,
    "8": 0.6892279490384737,
    "9": 0.6685151839826614,
    "10": 0.6494591607009937,
    "11": 0.6312314875354552,
    "12": 0.6131922666337117,
    "13": 0.5958921118549656,
    "14": 0.5793657493739309,
    "15": 0.5638016807689371,
    "16": 0.548867556327012,
    "17": 0.5342756692020262,
    "18": 0.5201053888398013,
    "19": 0.5064559271487853,
    "20": 0.4931685493719061
  },
  "rho_1": 0.9024983199480066,
  "rho_1_p_value": 0.0,
  "lob_attached": false,
  "lob_source": "synthetic_trade_imbalance",
  "obi_source": "trade_volume_imbalance",
  "obi_is_proxy": true,
  "obi_causal": true,
  "obi_valid_rows": 815215,
  "obi_valid_fraction": 0.9999754671965753,
  "obi_formula": "(rolling_buy_volume-rolling_sell_volume)/(rolling_buy_volume+rolling_sell_volume)",
  "obi_window_trades": 100,
  "obi_min_periods": 20,
  "obi_lag_trades": 1,
  "trade_intensity_causal": true,
  "trade_intensity_definition": "number_of_observed_trades_so_far_in_current_epoch_second",
  "lob_matched_rows": 0,
  "lob_match_fraction": 0.0,
  "minimum_lob_match_fraction": null
}